clarion/__init__.py
clarion/clarion.py
clarion-0.1.0.dist-info/licenses/LICENSE
clarion-0.1.0.dist-info/METADATA
clarion-0.1.0.dist-info/WHEEL
clarion-0.1.0.dist-info/top_level.txt
clarion-0.1.0.dist-info/RECORD
