Metadata-Version: 2.4
Name: clarion
Version: 0.1.0
Summary: A Python package for advanced data classification.
Author-email: "Chinmay (Chish)" <chishxd@tutamail.com>
License-Expression: MIT
Project-URL: Homepage, https://github.com/chishxd/clarion
Project-URL: Issues, https://github.com/chishxd/clarion/issues
Classifier: Programming Language :: Python :: 3
Classifier: Operating System :: OS Independent
Requires-Python: >=3.8
License-File: LICENSE
Requires-Dist: pandas
Requires-Dist: boto3
Dynamic: license-file
